pywikiscraper/__init__.py
pywikiscraper-0.0.5.dist-info/LICENSE
pywikiscraper-0.0.5.dist-info/METADATA
pywikiscraper-0.0.5.dist-info/WHEEL
pywikiscraper-0.0.5.dist-info/top_level.txt
pywikiscraper-0.0.5.dist-info/RECORD
