Metadata-Version: 2.1
Name: pywikiscraper
Version: 0.0.5
Summary: A litte package to easy scrape any wikipedia page
Home-page: https://github.com/frier-sam/pywikiscraper
Author: sam-iau
Author-email: sam-iau@outlook.com
License: UNKNOWN
Platform: UNKNOWN
Classifier: Programming Language :: Python :: 3.6
Classifier: License :: OSI Approved :: MIT License
Classifier: Operating System :: OS Independent
Requires-Dist: requests (==2.19.1)
Requires-Dist: lxml (==4.2.5)
